[{"grade": "1", "class_id": "1105123", "class_num": "01", "class_name": "\u8fd1\u73fe\u4ee3\u5b78\u8853\u601d\u60f3\u5c08\u984cSeminar on Modern Chinese Thoughts ", "teacher": "\u9673\u4fca\u555f ", "credit": "3", "category": "\u9078\u4fee", "time": " \u4e093,4,5", "location": "\u6587\u5b78\u9662202", "limit_people": "0", "outline": "http://ecourse.ccu.edu.tw/php/Courses_Admin/guest3.php?PHPSESSID=0466f8e4b492c9294334e34ad49e1de8&courseno=1105123_01&year=107&term=2", "note": ""}, {"grade": "1", "class_id": "1105191", "class_num": "01", "class_name": "\u4e2d\u570b\u54f2\u5b78\u554f\u984c\u5c08\u984c\u7814\u7a76The Seminar of Chinese Philosophy on Classical Issues ", "teacher": "\u9673\u4f73\u9298 ", "credit": "3", "category": "\u9078\u4fee", "time": " \u56db3,4,5", "location": "\u6587\u5b78\u9662201", "limit_people": "0", "outline": "http://ecourse.ccu.edu.tw/php/Courses_Admin/guest3.php?PHPSESSID=0466f8e4b492c9294334e34ad49e1de8&courseno=1105191_01&year=107&term=2", "note": ""}, {"grade": "1", "class_id": "1105493", "class_num": "01", "class_name": "\u7d93\u5b78\u53f2\u7814\u7a76Study of History of Chinese Classical Canons ", "teacher": "\u5f35\u66f8\u8c6a ", "credit": "3", "category": "\u9078\u4fee", "time": " \u4e8c7,8,9", "location": "\u6587\u5b78\u9662201", "limit_people": "0", "outline": "http://ecourse.ccu.edu.tw/php/Courses_Admin/guest3.php?PHPSESSID=0466f8e4b492c9294334e34ad49e1de8&courseno=1105493_01&year=107&term=2", "note": ""}, {"grade": "1", "class_id": "1105914", "class_num": "01", "class_name": "\u5730\u65b9\u77e5\u8b58\u3001\u6df1\u5ea6\u5831\u5c0e\u8207\u7d00\u9304\u7247\u88fd\u4f5c\uff08\u4e00\uff09Local Knowledge, In-depth Reporting and Documentary Films Production (I) ", "teacher": "\u6c5f\u5bf6\u91f5 \u738b\u842c\u777f \u674e\u77e5\u705d ", "credit": "3", "category": "\u9078\u4fee", "time": " \u4e8c10,11,12", "location": "\u6587\u5b78\u9662202", "limit_people": "0", "outline": "http://ecourse.ccu.edu.tw/php/Courses_Admin/guest3.php?PHPSESSID=0466f8e4b492c9294334e34ad49e1de8&courseno=1105914_01&year=107&term=2", "note": "\u672c\u8ab2\u7a0b\u4fee(\u4e00)\u4e0d\u5fc5\u4fee(\u4e8c)\u5373\u53ef\u8a8d\u5217\u70ba\u5c08\u696d\u9078\u4fee\u8ab2\u7a0b\u3002"}, {"grade": "1", "class_id": "1105964", "class_num": "01", "class_name": "\u6e05\u672b\u6c11\u521d\u5973\u4f5c\u5bb6\u5c08\u984c\u7814\u7a76Seminar on Women Writers in Late Qing and Early Republican Period ", "teacher": "\u9ec3\u9326\u73e0 ", "credit": "3", "category": "\u9078\u4fee", "time": " \u4e8c3,4,5", "location": "\u6587\u5b78\u9662202", "limit_people": "0", "outline": "http://ecourse.ccu.edu.tw/php/Courses_Admin/guest3.php?PHPSESSID=0466f8e4b492c9294334e34ad49e1de8&courseno=1105964_01&year=107&term=2", "note": ""}, {"grade": "1", "class_id": "1106414", "class_num": "01", "class_name": "\u5de6\u50b3\u5b78\u5c08\u984c\u7814\u7a76Monographic  Studies  of  Zuo  Zhuan ", "teacher": "\u9673\u97fb ", "credit": "3", "category": "\u9078\u4fee", "time": " \u4e0910,11,12", "location": "\u6587\u5b78\u9662202", "limit_people": "0", "outline": "http://ecourse.ccu.edu.tw/php/Courses_Admin/guest3.php?PHPSESSID=0466f8e4b492c9294334e34ad49e1de8&courseno=1106414_01&year=107&term=2", "note": ""}, {"grade": "1", "class_id": "1106877", "class_num": "01", "class_name": "\u4e2d\u570b\u5c0f\u8aaa\u53f2\u5c08\u984c\u7814\u7a76Studies on History of Chinese Novels ", "teacher": "\u738b\u74ca\u73b2 ", "credit": "3", "category": "\u9078\u4fee", "time": " \u4e0010,11,12", "location": "\u6587\u5b78\u9662201", "limit_people": "0", "outline": "http://ecourse.ccu.edu.tw/php/Courses_Admin/guest3.php?PHPSESSID=0466f8e4b492c9294334e34ad49e1de8&courseno=1106877_01&year=107&term=2", "note": ""}, {"grade": "1", "class_id": "1106913", "class_num": "01", "class_name": "\u6771\u4e9e\u6587\u5316\u8207\u8d8a\u5357\u6f22\u5b78\u5c08\u984cStudy on East Asian Cultural and Vietnam Sinology ", "teacher": "\u803f\u6167\u73b2 ", "credit": "3", "category": "\u9078\u4fee", "time": " \u4e943,4,5", "location": "\u6587\u5b78\u9662201", "limit_people": "0", "outline": "http://ecourse.ccu.edu.tw/php/Courses_Admin/guest3.php?PHPSESSID=0466f8e4b492c9294334e34ad49e1de8&courseno=1106913_01&year=107&term=2", "note": ""}]