[{"limit_people": "0", "grade": "1", "credit": "3", "time": " \u4e8c3,4,5", "location": "\u5316\u751f\u7cfb502", "teacher": "\u6731\u5ef6\u548c ", "note": "", "class_name": "\u751f\u5316\u5206\u5b50Biomolecules ", "outline": "http://ecourse.ccu.edu.tw/php/Courses_Admin/guest3.php?PHPSESSID=0466f8e4b492c9294334e34ad49e1de8&courseno=2605237_01&year=108&term=1", "category": "\u9078\u4fee", "class_id": "2605237", "class_num": "01"}, {"limit_people": "0", "grade": "1", "credit": "3", "time": " \u4e94C,D", "location": "\u5316\u751f\u7cfb319", "teacher": "\u6d2a\u4f2f\u8aa0 ", "note": "", "class_name": "\u6709\u6a5f\u5149\u8b5c\u5206\u6790\u5316\u5b78\uff08\u4e8c\uff09Organic Spectroscopic Analysis (II) ", "outline": "http://ecourse.ccu.edu.tw/php/Courses_Admin/guest3.php?PHPSESSID=0466f8e4b492c9294334e34ad49e1de8&courseno=2605242_01&year=108&term=1", "category": "\u9078\u4fee", "class_id": "2605242", "class_num": "01"}, {"limit_people": "0", "grade": "1", "credit": "3", "time": " \u4e8cB,C", "location": "\u5316\u751f\u7cfb102", "teacher": "\u4e8e\u6dd1\u541b ", "note": "", "class_name": "\u6709\u6a5f\u91d1\u5c6c\u5316\u5b78Organometallic Chemistry (\u5168\u82f1\u8a9e\u6388\u8ab2/English-taught) ", "outline": "http://ecourse.ccu.edu.tw/php/Courses_Admin/guest3.php?PHPSESSID=0466f8e4b492c9294334e34ad49e1de8&courseno=2605328_01&year=108&term=1", "category": "\u9078\u4fee", "class_id": "2605328", "class_num": "01"}, {"limit_people": "0", "grade": "1", "credit": "3", "time": " \u56db3,4,5", "location": "\u5316\u751f\u7cfb502", "teacher": "\u5409\u51f1\u660e ", "note": "", "class_name": "\u7121\u6a5f\u5149\u8b5c\u5316\u5b78Inorganic Spectroscopic Chemistry ", "outline": "http://ecourse.ccu.edu.tw/php/Courses_Admin/guest3.php?PHPSESSID=0466f8e4b492c9294334e34ad49e1de8&courseno=2605338_01&year=108&term=1", "category": "\u9078\u4fee", "class_id": "2605338", "class_num": "01"}, {"limit_people": "0", "grade": "1", "credit": "3", "time": " \u4e8cB \u56dbB", "location": "\u5316\u751f\u7cfb402", "teacher": "\u674e\u932b\u9686 ", "note": "", "class_name": "\u9ad8\u7b49\u91cf\u5b50\u5316\u5b78Advanced Quantum Chemistry ", "outline": "http://ecourse.ccu.edu.tw/php/Courses_Admin/guest3.php?PHPSESSID=0466f8e4b492c9294334e34ad49e1de8&courseno=2605417_01&year=108&term=1", "category": "\u9078\u4fee", "class_id": "2605417", "class_num": "01"}, {"limit_people": "0", "grade": "1", "credit": "3", "time": " \u4e00B,C", "location": "\u5316\u751f\u7cfb402", "teacher": "\u6797\u7fa4\u6b3d ", "note": "", "class_name": "\u5316\u5b78\u52d5\u529b\u5b78\uff08\u4e8c\uff09Chemical Kinetics (II) ", "outline": "http://ecourse.ccu.edu.tw/php/Courses_Admin/guest3.php?PHPSESSID=0466f8e4b492c9294334e34ad49e1de8&courseno=2605422_01&year=108&term=1", "category": "\u9078\u4fee", "class_id": "2605422", "class_num": "01"}, {"limit_people": "0", "grade": "1", "credit": "3", "time": " \u4e8cB,C", "location": "\u5316\u751f\u7cfb317", "teacher": "\u738b\u5c11\u541b ", "note": "", "class_name": "\u5149\u8b5c\u5316\u5b78\u5206\u6790\u8207\u5316\u5b78\u8a08\u91cf\u5b78Spectrochemical Analysis and Chemometrics ", "outline": "http://ecourse.ccu.edu.tw/php/Courses_Admin/guest3.php?PHPSESSID=0466f8e4b492c9294334e34ad49e1de8&courseno=2605507_01&year=108&term=1", "category": "\u9078\u4fee", "class_id": "2605507", "class_num": "01"}, {"limit_people": "0", "grade": "1", "credit": "3", "time": " \u4e094,5 \u4e944", "location": "\u5316\u751f\u7cfb317", "teacher": "\u9b4f\u570b\u4f50 ", "note": "", "class_name": "\u5206\u96e2\u65b9\u6cd5Analytical Separation Methods ", "outline": "http://ecourse.ccu.edu.tw/php/Courses_Admin/guest3.php?PHPSESSID=0466f8e4b492c9294334e34ad49e1de8&courseno=2605527_01&year=108&term=1", "category": "\u9078\u4fee", "class_id": "2605527", "class_num": "01"}, {"limit_people": "0", "grade": "1", "credit": "3", "time": " \u56db3,4,5", "location": "\u5316\u751f\u7cfb317", "teacher": "\u6e38\u666f\u6674 ", "note": "", "class_name": "\u5316\u5b78\u751f\u7269\u5b78Chemical Biology ", "outline": "http://ecourse.ccu.edu.tw/php/Courses_Admin/guest3.php?PHPSESSID=0466f8e4b492c9294334e34ad49e1de8&courseno=2605528_01&year=108&term=1", "category": "\u9078\u4fee", "class_id": "2605528", "class_num": "01"}, {"limit_people": "0", "grade": "1", "credit": "3", "time": " \u56dbC,D", "location": "\u5316\u751f\u7cfb402", "teacher": "\u9673\u7693\u541b ", "note": "", "class_name": "\u751f\u7269\u5206\u6790\u5316\u5b78\uff08\u4e00\uff09Bioanalytical Chemistry (I) ", "outline": "http://ecourse.ccu.edu.tw/php/Courses_Admin/guest3.php?PHPSESSID=0466f8e4b492c9294334e34ad49e1de8&courseno=2605531_01&year=108&term=1", "category": "\u9078\u4fee", "class_id": "2605531", "class_num": "01"}, {"limit_people": "0", "grade": "1", "credit": "3", "time": " \u4e09B,C", "location": "\u5316\u751f\u7cfb116", "teacher": "\u738b\u5d07\u4eba ", "note": "", "class_name": "\u5948\u7c73\u6750\u6599\u79d1\u5b78Nanostructured Material Science ", "outline": "http://ecourse.ccu.edu.tw/php/Courses_Admin/guest3.php?PHPSESSID=0466f8e4b492c9294334e34ad49e1de8&courseno=2605707_01&year=108&term=1", "category": "\u9078\u4fee", "class_id": "2605707", "class_num": "01"}, {"limit_people": "0", "grade": "1", "credit": "2", "time": " \u4e0910,11", "location": "\u5316\u751f\u7cfb317", "teacher": "\u5433\u69ae\u5b97 ", "note": "", "class_name": "\u5de5\u696d\u89f8\u5a92\u5316\u5b78Industrial Catalytic Chemistry ", "outline": "http://ecourse.ccu.edu.tw/php/Courses_Admin/guest3.php?PHPSESSID=0466f8e4b492c9294334e34ad49e1de8&courseno=2605717_01&year=108&term=1", "category": "\u9078\u4fee", "class_id": "2605717", "class_num": "01"}, {"limit_people": "0", "grade": "1", "credit": "1", "time": " \u56db8,9", "location": "\u5316\u751f\u7cfb319", "teacher": "\u6731\u5ef6\u548c ", "note": "\u78a9\u4e00\u8207\u535a\u4e00\r", "class_name": "\u6709\u6a5f\u5316\u5b78\u66f8\u5831\u8a0e\u8ad6\uff08\u4e00\uff09Organic Chemistry Seminar (I) ", "outline": "http://ecourse.ccu.edu.tw/php/Courses_Admin/guest3.php?PHPSESSID=0466f8e4b492c9294334e34ad49e1de8&courseno=2605901_01&year=108&term=1", "category": "\u5fc5\u4fee", "class_id": "2605901", "class_num": "01"}, {"limit_people": "0", "grade": "1", "credit": "1", "time": " \u56db8,9", "location": "\u5316\u751f\u7cfb319", "teacher": "\u6731\u5ef6\u548c ", "note": "\u78a9\u4e8c\u8207\u535a\u4e8c\r", "class_name": "\u6709\u6a5f\u5316\u5b78\u66f8\u5831\u8a0e\u8ad6\uff08\u4e09\uff09Organic Chemistry Seminar (III) ", "outline": "http://ecourse.ccu.edu.tw/php/Courses_Admin/guest3.php?PHPSESSID=0466f8e4b492c9294334e34ad49e1de8&courseno=2605902_01&year=108&term=1", "category": "\u5fc5\u4fee", "class_id": "2605902", "class_num": "01"}, {"limit_people": "0", "grade": "1", "credit": "1", "time": " \u4e008,9", "location": "\u5316\u751f\u7cfb317", "teacher": "\u5ed6\u5112\u4fee ", "note": "\u78a9\u4e00\u8207\u535a\u4e00\r", "class_name": "\u7121\u6a5f\u5316\u5b78\u66f8\u5831\u8a0e\u8ad6\uff08\u4e00\uff09Inorganic Chemistry Seminar (I) ", "outline": "http://ecourse.ccu.edu.tw/php/Courses_Admin/guest3.php?PHPSESSID=0466f8e4b492c9294334e34ad49e1de8&courseno=2605905_01&year=108&term=1", "category": "\u5fc5\u4fee", "class_id": "2605905", "class_num": "01"}, {"limit_people": "0", "grade": "1", "credit": "1", "time": " \u4e008,9", "location": "\u5316\u751f\u7cfb317", "teacher": "\u5ed6\u5112\u4fee ", "note": "\u78a9\u4e8c\u8207\u535a\u4e8c\r", "class_name": "\u7121\u6a5f\u5316\u5b78\u66f8\u5831\u8a0e\u8ad6\uff08\u4e09\uff09Inorganic Chemistry Seminar (III) ", "outline": "http://ecourse.ccu.edu.tw/php/Courses_Admin/guest3.php?PHPSESSID=0466f8e4b492c9294334e34ad49e1de8&courseno=2605906_01&year=108&term=1", "category": "\u5fc5\u4fee", "class_id": "2605906", "class_num": "01"}, {"limit_people": "0", "grade": "1", "credit": "1", "time": " \u4e008,9", "location": "\u5316\u751f\u7cfb116", "teacher": "\u738b\u5d07\u4eba ", "note": "\u78a9\u4e00\u8207\u535a\u4e00\r", "class_name": "\u7269\u7406\u5316\u5b78\u66f8\u5831\u8a0e\u8ad6\uff08\u4e00\uff09Physical Chemistry Seminar (I) ", "outline": "http://ecourse.ccu.edu.tw/php/Courses_Admin/guest3.php?PHPSESSID=0466f8e4b492c9294334e34ad49e1de8&courseno=2605909_01&year=108&term=1", "category": "\u5fc5\u4fee", "class_id": "2605909", "class_num": "01"}, {"limit_people": "0", "grade": "1", "credit": "1", "time": " \u4e008,9", "location": "\u5316\u751f\u7cfb116", "teacher": "\u738b\u5d07\u4eba ", "note": "\u78a9\u4e8c\u8207\u535a\u4e8c\r", "class_name": "\u7269\u7406\u5316\u5b78\u66f8\u5831\u8a0e\u8ad6\uff08\u4e09\uff09Physical Chemistry Seminar (III) ", "outline": "http://ecourse.ccu.edu.tw/php/Courses_Admin/guest3.php?PHPSESSID=0466f8e4b492c9294334e34ad49e1de8&courseno=2605910_01&year=108&term=1", "category": "\u5fc5\u4fee", "class_id": "2605910", "class_num": "01"}, {"limit_people": "0", "grade": "1", "credit": "1", "time": " \u4e008,9", "location": "\u5316\u751f\u7cfb319", "teacher": "\u738b\u5c11\u541b ", "note": "\u78a9\u4e00\u8207\u535a\u4e00\r", "class_name": "\u5206\u6790\u5316\u5b78\u66f8\u5831\u8a0e\u8ad6\uff08\u4e00\uff09Analytical Chemistry Seminar (I) ", "outline": "http://ecourse.ccu.edu.tw/php/Courses_Admin/guest3.php?PHPSESSID=0466f8e4b492c9294334e34ad49e1de8&courseno=2605913_01&year=108&term=1", "category": "\u5fc5\u4fee", "class_id": "2605913", "class_num": "01"}, {"limit_people": "0", "grade": "1", "credit": "1", "time": " \u4e008,9", "location": "\u5316\u751f\u7cfb319", "teacher": "\u738b\u5c11\u541b ", "note": "\u78a9\u4e8c\u8207\u535a\u4e8c\r", "class_name": "\u5206\u6790\u5316\u5b78\u66f8\u5831\u8a0e\u8ad6\uff08\u4e09\uff09Analytical Chemistry Seminar (III) ", "outline": "http://ecourse.ccu.edu.tw/php/Courses_Admin/guest3.php?PHPSESSID=0466f8e4b492c9294334e34ad49e1de8&courseno=2605914_01&year=108&term=1", "category": "\u5fc5\u4fee", "class_id": "2605914", "class_num": "01"}]