[{"grade": "1", "class_id": "5455005", "class_num": "01", "class_name": "\u7814\u7a76\u65b9\u6cd5Research Methods ", "teacher": "\u838a\u4e16\u6770 \u8607\u5b8f\u4ec1 ", "credit": "3", "category": "\u5fc5\u4fee", "time": " \u4e8c3,4,5", "location": "\u7ba1\u7406\u5b78\u9662454", "limit_people": "0", "outline": "http://ecourse.ccu.edu.tw/php/Courses_Admin/guest3.php?PHPSESSID=0466f8e4b492c9294334e34ad49e1de8&courseno=5455005_01&year=107&term=2", "note": ""}, {"grade": "1", "class_id": "5455042", "class_num": "01", "class_name": "\u7db2\u8def\u884c\u92b7Internet Marketing ", "teacher": "\u8607\u5b8f\u4ec1 ", "credit": "3", "category": "\u9078\u4fee", "time": " \u56db7,8,9", "location": "\u7ba1\u7406\u5b78\u9662454", "limit_people": "0", "outline": "http://ecourse.ccu.edu.tw/php/Courses_Admin/guest3.php?PHPSESSID=0466f8e4b492c9294334e34ad49e1de8&courseno=5455042_01&year=107&term=2", "note": ""}, {"grade": "1", "class_id": "5455070", "class_num": "01", "class_name": "\u884c\u92b7\u6587\u6848\u5beb\u4f5c\u8207\u6e9d\u901aMarketing Copywriting and Communication ", "teacher": "\u66fe\u5149\u83ef ", "credit": "3", "category": "\u9078\u4fee", "time": " \u4e094,5,6", "location": "\u7ba1\u7406\u5b78\u9662441\u7814\u8a0e\u5ba4", "limit_people": "30", "outline": "http://ecourse.ccu.edu.tw/php/Courses_Admin/guest3.php?PHPSESSID=0466f8e4b492c9294334e34ad49e1de8&courseno=5455070_01&year=107&term=2", "note": ""}, {"grade": "1", "class_id": "5455073", "class_num": "01", "class_name": "\u96f6\u552e\u7ba1\u7406Retailing Management ", "teacher": "\u6e38\u84d3\u6021 ", "credit": "3", "category": "\u9078\u4fee", "time": " \u56db4,5,6", "location": "\u7ba1\u7406\u5b78\u9662454", "limit_people": "0", "outline": "http://ecourse.ccu.edu.tw/php/Courses_Admin/guest3.php?PHPSESSID=0466f8e4b492c9294334e34ad49e1de8&courseno=5455073_01&year=107&term=2", "note": "\u5148\u4fee\u79d1\u76ee(5455001)\u884c\u92b7\u7ba1\u7406(\u53ca\u683c) (5205006)\u884c\u92b7\u7ba1\u7406(\u53ca\u683c) (\u53ea\u8981\u7b26\u5408\u4efb\u4e00\u5148\u4fee\u689d\u4ef6)\u6b61\u8fce\u672c\u7cfb\u5927\u4e09\u3001\u56db\u5b78\u751f\u4fee\u8b80"}]